gtirb_types/__init__.py
gtirb_types/display.py
gtirb_types/graph.py
gtirb_types/types.py
gtirb_types/version.py
gtirb_types-0.2.0.dist-info/LICENSE.txt
gtirb_types-0.2.0.dist-info/METADATA
gtirb_types-0.2.0.dist-info/WHEEL
gtirb_types-0.2.0.dist-info/entry_points.txt
gtirb_types-0.2.0.dist-info/top_level.txt
gtirb_types-0.2.0.dist-info/RECORD
